<?xml version="1.0" encoding="utf-8"?>
<DynamicsProperties>
  <DynamicPropertiesCategory Category="3D Component">
    <DynamicProperty>Title</DynamicProperty>
    <DynamicProperty>Description</DynamicProperty>
    <DynamicProperty>Part Number</DynamicProperty>
    <DynamicProperty>Material</DynamicProperty>
    <DynamicProperty>Dimensions</DynamicProperty>
    <DynamicProperty>Mass</DynamicProperty>
    <DynamicProperty>Spare-Wear Part</DynamicProperty>
    <DynamicProperty>Semi finished</DynamicProperty>
    <DynamicProperty>Stock Number</DynamicProperty>
    <DynamicProperty Hidden="True">G_L</DynamicProperty>
    <DynamicProperty Hidden="True">PL</DynamicProperty>
    <DynamicProperty>Source File</DynamicProperty>
    <DynamicProperty Hidden="True">LastUpdatedWith</DynamicProperty>
  </DynamicPropertiesCategory>
  <DynamicPropertiesCategory Category="Part" Type="File">
    <DynamicProperty>Title</DynamicProperty>
    <DynamicProperty>Material</DynamicProperty>
    <DynamicProperty>Part Number</DynamicProperty>
    <DynamicProperty>Weight</DynamicProperty>
    <DynamicProperty>Spare-Wear Part</DynamicProperty>
    <DynamicProperty>Dimensions/Size</DynamicProperty>
    <DynamicProperty>Description 2</DynamicProperty>
    <DynamicProperty>Description</DynamicProperty>
    <DynamicProperty>Stock Number</DynamicProperty>
    <DynamicProperty>Length (Cut)</DynamicProperty>
    <DynamicProperty>Semi finished</DynamicProperty>
    <DynamicProperty>Ident Number</DynamicProperty>
    <DynamicProperty>Project Number</DynamicProperty>
    <DynamicProperty>Source File</DynamicProperty>
    <DynamicProperty>Author</DynamicProperty>
    <DynamicProperty>Project</DynamicProperty>
    <DynamicProperty>Mfg Approved By</DynamicProperty>
    <DynamicProperty>Manager</DynamicProperty>
    <DynamicProperty>Engr Approved By</DynamicProperty>
    <DynamicProperty>FDS Key</DynamicProperty>
    <DynamicProperty>Designer</DynamicProperty>
    <DynamicProperty>Engineer</DynamicProperty>
    <DynamicProperty>Comments</DynamicProperty>
    <DynamicProperty>Cost</DynamicProperty>
    <DynamicProperty>Keywords</DynamicProperty>
    <DynamicProperty>Subject</DynamicProperty>
    <DynamicProperty>Company</DynamicProperty>
    <DynamicProperty>Project Type</DynamicProperty>
    <DynamicProperty>Checked By</DynamicProperty>
    <DynamicProperty>LastUpdatedWith</DynamicProperty>
    <DynamicProperty Hidden="True">Part Type name</DynamicProperty>
    <DynamicProperty>G_L</DynamicProperty>
    <DynamicProperty>Dimensions</DynamicProperty>
    <DynamicProperty>Mass</DynamicProperty>
    <DynamicProperty>Engr Approved by</DynamicProperty>
    <DynamicProperty>Title DE</DynamicProperty>
    <DynamicProperty>Has MBD</DynamicProperty>
    <DynamicProperty>Key Parameters</DynamicProperty>
    <DynamicProperty>Part Family</DynamicProperty>
  </DynamicPropertiesCategory>
  <DynamicPropertiesCategory Category="Assembly" Type="File">
    <DynamicProperty>Title</DynamicProperty>
    <DynamicProperty>Material</DynamicProperty>
    <DynamicProperty>Part Number</DynamicProperty>
    <DynamicProperty>Weight</DynamicProperty>
    <DynamicProperty>Spare-Wear Part</DynamicProperty>
    <DynamicProperty>Dimensions/Size</DynamicProperty>
    <DynamicProperty>Description 2</DynamicProperty>
    <DynamicProperty>Description</DynamicProperty>
    <DynamicProperty>Stock Number</DynamicProperty>
    <DynamicProperty>Length (Cut)</DynamicProperty>
    <DynamicProperty>Semi finished</DynamicProperty>
    <DynamicProperty>Ident Number</DynamicProperty>
    <DynamicProperty>Project Number</DynamicProperty>
    <DynamicProperty>Source File</DynamicProperty>
    <DynamicProperty>Author</DynamicProperty>
    <DynamicProperty>Project</DynamicProperty>
    <DynamicProperty>Mfg Approved By</DynamicProperty>
    <DynamicProperty>Manager</DynamicProperty>
    <DynamicProperty>Engr Approved By</DynamicProperty>
    <DynamicProperty>FDS Key</DynamicProperty>
    <DynamicProperty>Designer</DynamicProperty>
    <DynamicProperty>Engineer</DynamicProperty>
    <DynamicProperty>Comments</DynamicProperty>
    <DynamicProperty>Cost</DynamicProperty>
    <DynamicProperty>Keywords</DynamicProperty>
    <DynamicProperty>Subject</DynamicProperty>
    <DynamicProperty>Company</DynamicProperty>
    <DynamicProperty>Project Type</DynamicProperty>
    <DynamicProperty>Checked By</DynamicProperty>
    <DynamicProperty>Dimensions</DynamicProperty>
    <DynamicProperty>LastUpdatedWith</DynamicProperty>
    <DynamicProperty>Mass</DynamicProperty>
    <DynamicProperty Hidden="True">Part Type name</DynamicProperty>
    <DynamicProperty>Engr Approved by</DynamicProperty>
    <DynamicProperty>Title DE</DynamicProperty>
    <DynamicProperty>Has MBD</DynamicProperty>
    <DynamicProperty>Key Parameters</DynamicProperty>
    <DynamicProperty>Part Family</DynamicProperty>
  </DynamicPropertiesCategory>
  <DynamicPropertiesCategory Category="Sheet Metal Part" Type="File">
    <DynamicProperty>Title</DynamicProperty>
    <DynamicProperty>Material</DynamicProperty>
    <DynamicProperty>Part Number</DynamicProperty>
    <DynamicProperty>Weight</DynamicProperty>
    <DynamicProperty>Spare-Wear Part</DynamicProperty>
    <DynamicProperty>Dimensions/Size</DynamicProperty>
    <DynamicProperty>Description 2</DynamicProperty>
    <DynamicProperty>Description</DynamicProperty>
    <DynamicProperty>Stock Number</DynamicProperty>
    <DynamicProperty>Length (Cut)</DynamicProperty>
    <DynamicProperty>Semi finished</DynamicProperty>
    <DynamicProperty>Ident Number</DynamicProperty>
    <DynamicProperty>Project Number</DynamicProperty>
    <DynamicProperty>Source File</DynamicProperty>
    <DynamicProperty>Author</DynamicProperty>
    <DynamicProperty>Project</DynamicProperty>
    <DynamicProperty>Mfg Approved By</DynamicProperty>
    <DynamicProperty>Manager</DynamicProperty>
    <DynamicProperty>Engr Approved By</DynamicProperty>
    <DynamicProperty>FDS Key</DynamicProperty>
    <DynamicProperty>Designer</DynamicProperty>
    <DynamicProperty>Engineer</DynamicProperty>
    <DynamicProperty>Comments</DynamicProperty>
    <DynamicProperty>Cost</DynamicProperty>
    <DynamicProperty>Keywords</DynamicProperty>
    <DynamicProperty>Subject</DynamicProperty>
    <DynamicProperty>Company</DynamicProperty>
    <DynamicProperty>Project Type</DynamicProperty>
    <DynamicProperty>Checked By</DynamicProperty>
    <DynamicProperty>LastUpdatedWith</DynamicProperty>
    <DynamicProperty>Part Type name</DynamicProperty>
    <DynamicProperty>G_L</DynamicProperty>
    <DynamicProperty>Dimensions</DynamicProperty>
    <DynamicProperty>Mass</DynamicProperty>
  </DynamicPropertiesCategory>
  <DynamicPropertiesCategory Category="Engineering">
    <DynamicProperty>Title</DynamicProperty>
    <DynamicProperty>Subject</DynamicProperty>
    <DynamicProperty>Description</DynamicProperty>
    <DynamicProperty>Part Number</DynamicProperty>
    <DynamicProperty>Project</DynamicProperty>
    <DynamicProperty>Material</DynamicProperty>
    <DynamicProperty>Checked by</DynamicProperty>
    <DynamicProperty>Engr Approved by</DynamicProperty>
    <DynamicProperty>Mfg Approved by</DynamicProperty>
    <DynamicProperty>Engineer</DynamicProperty>
    <DynamicProperty>Stock Number</DynamicProperty>
    <DynamicProperty>Cost</DynamicProperty>
    <DynamicProperty>Designer</DynamicProperty>
    <DynamicProperty>Author</DynamicProperty>
    <DynamicProperty>Manager</DynamicProperty>
    <DynamicProperty>Company</DynamicProperty>
    <DynamicProperty>Comments</DynamicProperty>
    <DynamicProperty>Keywords</DynamicProperty>
  </DynamicPropertiesCategory>
  <DynamicPropertiesCategory Category="Drawing Inventor">
    <DynamicProperty Hidden="True">Ident Number</DynamicProperty>
    <DynamicProperty>Title</DynamicProperty>
    <DynamicProperty>Description</DynamicProperty>
    <DynamicProperty>Part Number</DynamicProperty>
    <DynamicProperty>Project Number</DynamicProperty>
    <DynamicProperty>Material</DynamicProperty>
    <DynamicProperty>Weight</DynamicProperty>
    <DynamicProperty>Dimensions</DynamicProperty>
    <DynamicProperty>Scale</DynamicProperty>
    <DynamicProperty>Sheet</DynamicProperty>
    <DynamicProperty>Format</DynamicProperty>
    <DynamicProperty>Source File</DynamicProperty>
    <DynamicProperty>Project Type</DynamicProperty>
    <DynamicProperty>Type</DynamicProperty>
    <DynamicProperty>LastUpdatedWith</DynamicProperty>
    <DynamicProperty>Engr Approved by</DynamicProperty>
    <DynamicProperty>Designer</DynamicProperty>
    <DynamicProperty>Title DE</DynamicProperty>
  </DynamicPropertiesCategory>
  <DynamicPropertiesCategory Category="3D Komponenten">
    <DynamicProperty>Titel</DynamicProperty>
    <DynamicProperty>Titel EN</DynamicProperty>
    <DynamicProperty>Description</DynamicProperty>
    <DynamicProperty>Part Number</DynamicProperty>
    <DynamicProperty>Material</DynamicProperty>
    <DynamicProperty>Abmessung/Halbzeug</DynamicProperty>
    <DynamicProperty>Halbzeug</DynamicProperty>
    <DynamicProperty>Bestandsnummer</DynamicProperty>
    <DynamicProperty>Gewicht</DynamicProperty>
    <DynamicProperty>EV-Kennung</DynamicProperty>
    <DynamicProperty>Dicke/Durchmesser</DynamicProperty>
    <DynamicProperty>Werksnorm</DynamicProperty>
    <DynamicProperty>Breite</DynamicProperty>
    <DynamicProperty>Länge</DynamicProperty>
    <DynamicProperty>Name des Bauteiltyps</DynamicProperty>
    <DynamicProperty Hidden="True">Identnummer</DynamicProperty>
    <DynamicProperty>Entstanden aus</DynamicProperty>
    <DynamicProperty Hidden="True">G_L</DynamicProperty>
  </DynamicPropertiesCategory>
  <DynamicPropertiesCategory Category="Asset Library">
    <DynamicProperty>Stock Number</DynamicProperty>
    <DynamicProperty>Key Parameters</DynamicProperty>
    <DynamicProperty>Description</DynamicProperty>
    <DynamicProperty>Title</DynamicProperty>
    <DynamicProperty>Part Number</DynamicProperty>
  </DynamicPropertiesCategory>
  <DynamicPropertiesCategory Category="Factory Asset">
    <DynamicProperty>Stock Number</DynamicProperty>
    <DynamicProperty>Type</DynamicProperty>
    <DynamicProperty>Key Parameters</DynamicProperty>
    <DynamicProperty>Title</DynamicProperty>
    <DynamicProperty>Part Number</DynamicProperty>
    <DynamicProperty>Description</DynamicProperty>
  </DynamicPropertiesCategory>
  <DynamicPropertiesCategory Category="Factory Layout">
    <DynamicProperty>Title</DynamicProperty>
    <DynamicProperty>Description</DynamicProperty>
    <DynamicProperty>Part Number</DynamicProperty>
    <DynamicProperty>Project</DynamicProperty>
    <DynamicProperty>Project Type</DynamicProperty>
    <DynamicProperty Hidden="True">Project Number</DynamicProperty>
  </DynamicPropertiesCategory>
  <DynamicPropertiesCategory Category="Substitute">
    <DynamicProperty>LastUpdatedWith</DynamicProperty>
    <DynamicProperty>Dimensions</DynamicProperty>
    <DynamicProperty>Source File</DynamicProperty>
    <DynamicProperty>Part Type name</DynamicProperty>
    <DynamicProperty>Title</DynamicProperty>
    <DynamicProperty>Part Number</DynamicProperty>
    <DynamicProperty>Description</DynamicProperty>
  </DynamicPropertiesCategory>
</DynamicsProperties>